{
    "variants": {
        "facing=north,state=off": { "model": "foundry:alloyfurnaceoff" },
        "facing=south,state=off": { "model": "foundry:alloyfurnaceoff", "y": 180 },
        "facing=west,state=off":  { "model": "foundry:alloyfurnaceoff", "y": 270 },
        "facing=east,state=off":  { "model": "foundry:alloyfurnaceoff", "y": 90 },
        "facing=north,state=on": { "model": "foundry:alloyfurnaceon" },
        "facing=south,state=on": { "model": "foundry:alloyfurnaceon", "y": 180 },
        "facing=west,state=on":  { "model": "foundry:alloyfurnaceon", "y": 270 },
        "facing=east,state=on":  { "model": "foundry:alloyfurnaceon", "y": 90 }
    }
}
